yxsql/__init__.py
yxsql/sqlite.py
yxsql/versions.py
yxsql-0.0.1.dist-info/LICENSE
yxsql-0.0.1.dist-info/METADATA
yxsql-0.0.1.dist-info/WHEEL
yxsql-0.0.1.dist-info/top_level.txt
yxsql-0.0.1.dist-info/RECORD
