Metadata-Version: 2.1
Name: yxsql
Version: 0.0.1
Summary: Xu Yuxing's personal sqlite orm.
Home-page: https://github.com/SouthernCD/yxsql
Author: Yuxing Xu
Author-email: xuyuxing@mail.kib.ac.cn
Requires-Python: >=3.5
License-File: LICENSE
Requires-Dist: yxutil
